ztfcheck/__init__.py
ztfcheck/image_funcs.py
ztfcheck/ztfcheck.py
ZTF_Check-1.0.1.dist-info/LICENSE
ZTF_Check-1.0.1.dist-info/METADATA
ZTF_Check-1.0.1.dist-info/WHEEL
ZTF_Check-1.0.1.dist-info/entry_points.txt
ZTF_Check-1.0.1.dist-info/top_level.txt
ZTF_Check-1.0.1.dist-info/RECORD
